_kongalib.cpython-314t-x86_64-linux-gnu.so
kongaui.py
kongautil.py
kongalib/__init__.py
kongalib/async_client.py
kongalib/client.py
kongalib/constants.json
kongalib/constants.py
kongalib/data_dictionary.py
kongalib/db.py
kongalib/expression.py
kongalib/json.py
kongalib/lex.py
kongalib/scripting.py
kongalib/yacc.py
kongalib.libs/libblkid-a9167753.so.1.1.0
kongalib.libs/libcap-16fca4d2.so.2.48
kongalib.libs/libdbus-1-142c15b3.so.3.19.7
kongalib.libs/libgcrypt-a1b5cc4c.so.20.2.5
kongalib.libs/libgpg-error-d4e115d0.so.0.24.2
kongalib.libs/liblz4-c23f16fe.so.1.8.3
kongalib.libs/liblzma-51a76f52.so.5.2.4
kongalib.libs/libmount-ec61bd71.so.1.1.0
kongalib.libs/libpcre2-8-516f4c9d.so.0.7.1
kongalib.libs/libselinux-d0805dcb.so.1
kongalib.libs/libsystemd-82f97eea.so.0.23.0
kongalib.libs/libuuid-95b83d40.so.1.3.0
kongalib-2.0.3.dist-info/METADATA
kongalib-2.0.3.dist-info/WHEEL
kongalib-2.0.3.dist-info/top_level.txt
kongalib-2.0.3.dist-info/zip-safe
kongalib-2.0.3.dist-info/RECORD
kongalib-2.0.3.dist-info/licenses/LICENSE
