Metadata-Version: 2.1
Name: kongalib
Version: 2.0.3
Summary: Konga client library
Author-email: EasyByte Software <konga@easybyte.it>
License: LGPL
Project-URL: homepage, https://github.com/easybyte-software/kongalib
Project-URL: documentation, https://public.easybyte.it/docs/current/technical/kongalib/index.html
Project-URL: repository, https://github.com/easybyte-software/kongalib.git
Keywords: konga,client,erp
Classifier: Natural Language :: Italian
Classifier: Programming Language :: Python
Classifier: Programming Language :: Python :: 3
Classifier: Programming Language :: Python :: 3 :: Only
Classifier: Programming Language :: Python :: 3.8
Classifier: Programming Language :: Python :: 3.9
Classifier: Programming Language :: Python :: 3.10
Classifier: Programming Language :: Python :: 3.11
Classifier: Programming Language :: Python :: 3.12
Classifier: Programming Language :: Python :: 3.13
Classifier: Programming Language :: Python :: 3.14
Classifier: Programming Language :: C++
Classifier: Development Status :: 5 - Production/Stable
Classifier: Environment :: Console
Classifier: Intended Audience :: Developers
Classifier: Intended Audience :: Information Technology
Classifier: Intended Audience :: Financial and Insurance Industry
Classifier: Operating System :: MacOS :: MacOS X
Classifier: Operating System :: Microsoft :: Windows
Classifier: Operating System :: POSIX :: Linux
Classifier: Topic :: Office/Business
Classifier: Topic :: Office/Business :: Financial
Classifier: Topic :: Software Development :: Libraries
Requires-Python: >=3.8
License-File: LICENSE
Requires-Dist: colorama
Requires-Dist: nest-asyncio
